_oll
oll
