Metadata-Version: 1.1
Name: oll
Version: 0.2.1
Summary: Online binary classification algorithms library (wrapper for OLL C++ library)
Home-page: https://github.com/ikegami-yukino/oll-python
Author: Yukino Ikegami
Author-email: yknikgm@gmail.com
License: UNKNOWN
Keywords: machine learning,online learning,perceptron,Passive Agressive,PA,ALMA,Confidence Weighted Linear-Classification
Platform: UNKNOWN
Classifier: Development Status :: 3 - Alpha
Classifier: Intended Audience :: Developers
Classifier: Intended Audience :: Science/Research
Classifier: License :: OSI Approved :: BSD License
Classifier: Programming Language :: Python :: 2.7
Classifier: Programming Language :: Python :: 3.4
Classifier: Programming Language :: Python :: 3.5
Classifier: Topic :: Scientific/Engineering :: Artificial Intelligence
Classifier: Topic :: Scientific/Engineering :: Information Analysis
Classifier: Topic :: Text Processing :: Linguistic
